Workbook
Name Nr: 'Analysis of project risks'!$A$7
Name RZ: 'Analysis of project risks'!$J$9:$J$27
Name Status: 'Analysis of project risks'!$N$9:$N$27

Sheet Cover sheet
A1: Risk Analysis M&A | C1: IT-as-is Manager | D1: Bosch CIO
C2: IT-Project Manager | D2: IT PM (Bosch-led)
A3: - Cover Sheet - | C3: PMI-Lead | D3: KPMG
B5: Information about the project and the risk analysis:
B6: Actions are tracked in
B10: Further information:
B15: Participants of latest meeting/update of risk analysis:
B16: Participant | D16: Department | F16: Function
F17: PMI-Lead
F18: IT-Project Manager
F19: PjQM
F20: Technical expert from project team
B29: The required signature of the risk analysis (PjM and PjQM) is covered by the signature of the respective QA.
B30: Document History:
B31: Change | D31: Version | E31: Date | F31: Changed by
D34: …
B47: The risk analysis has to be updated regularly during the whole merger duration - The different states have to be versioned -

Sheet Analysis of project risks
A1: Analysis of as-is operation risks | K1: RZ statistic | M1: Please insert rows exclusively over button!
A2: ='Cover sheet'!C1 -> IT-as-is Manager | D2: ='Cover sheet'!D1 -> Bosch CIO | F2: ='[1]Cover sheet'!F1 -> 0 | G2: ='[1]Cover sheet'!G1 -> 0 | K2: Threshold: | L2: 12
A3: ='Cover sheet'!C2 -> IT-Project Manager | D3: ='Cover sheet'!D2 -> IT PM (Bosch-led) | F3: ='[1]Cover sheet'!F2 -> 0 | G3: ='[1]Cover sheet'!G2 -> 0 | K3: Risks higher than or equal to threshold: | L3: =COUNTIF(J9:J489,">="&L2) -> 10
A4: ='Cover sheet'!C3 -> PMI-Lead | D4: ='Cover sheet'!D3 -> KPMG | F4: ='[1]Cover sheet'!F3 -> 0 | G4: ='[1]Cover sheet'!G3 -> 0
A7: No. | B7: Sub- project (optional) | C7: Entry Date of Risk | D7: Risk category | E7: Risk (concrete, understandable description) | F7: Effects (corresponds with T=Sign. of effects (column I)) | G7: Causes | H7: W | I7: T | J7: RZ | K7: Actions (preventive and counter measures) | L7: Responsible | M7: Deadline | N7: Status of action | O7: Remarks / notes [optional] (e.g., critical general conditions; already planned actions)
A9: 1 | B9: Phase 1 – Governance | C9: 2026-07-01 | D9: ScR = Schedule | E9: IT project leadership not appointed on time by Bosch and JCI | F9: Delayed project kick-off; governance vacuum; Phase 1 milestones slip | G9: Executive bandwidth constraints; unclear mandate between Bosch CIO and JCI CIO | H9: 2 | I9: 4 | J9: =$H9*$I9 -> 8 | K9: Escalate appointment to ExCo by project start date; confirm names in SPA pre-conditions | L9: Bosch CIO + JCI CIO | M9: 2026-07-14 | N9: Open | O9: Prerequisite for all Phase 1 activities
A10: 2 | B10: Phase 1 – Governance | C10: 2026-07-01 | D10: SR = Scope | E10: Governance model and RACI not agreed between Bosch and JCI within Initialization | F10: Unclear decision authority; stalled workstream progress; Steering Committee ineffective | G10: Differing governance expectations; prior relationship between JCI and Bosch not yet formalised | H10: 2 | I10: 3 | J10: =$H10*$I10 -> 6 | K10: RACI workshop facilitated by KPMG by week 2; escalation matrix agreed before QG1 | L10: KPMG + IT PM | M10: 2026-07-20 | N10: Open | O10: FRAME precedent: RACI agreed in first 4 weeks
A11: 3 | B11: Phase 1 – Scope | C11: 2026-07-01 | D11: SR = Scope | E11: 180-site location list incomplete or inaccurate | F11: Infrastructure design based on wrong site count; wave planning errors; budget miscalculation | G11: JCI facilities data fragmented across regions; AP/AM site data not centrally maintained | H11: 3 | I11: 3 | J11: =$H11*$I11 -> 9 | K11: Mandate JCI Facilities to submit full site list with addresses and types by week 3; validate against HR headcount data | L11: JCI IT + Facilities | M11: 2026-08-24 | N11: Open | O11: 180 sites confirmed as baseline; AP and AM are largest regions
A12: 4 | B12: Phase 1 – Legal | C12: 2026-07-01 | D12: LR = Legality | E12: Legal entity identification delayed — especially Mexico, China, India | F12: ERP country go-live excluded; manual compliance workarounds; SPA conditions not met | G12: Complex local registration processes; bank account setup delays; tax authority lead times | H12: 4 | I12: 3 | J12: =$H12*$I12 -> 12 | K12: Engage local legal counsel per country by Phase 1; Mexico contingency plan (phased go-live); India RBIN exception initiated with Bosch CISO | L12: Legal + Finance | M12: 2026-08-28 | N12: Open | O12: Brazil/China/India/Mexico flagged as high-complexity in CLAUDE.md
A13: 5 | B13: Phase 1 – TSA | C13: 2026-07-01 | D13: SR = Scope | E13: TSA framework not agreed before QG1; 18-month scope and service catalogue disputed | F13: TSA cannot be operationalised; service gaps on Day 1; JCI obligations unclear | G13: JCI and Bosch not aligned on which services are included; pricing model disputed | H13: 2 | I13: 4 | J13: =$H13*$I13 -> 8 | K13: TSA preliminary framework defined by Legal and IT PM before QG1; catalogue refined in Phase 2 | L13: Legal + IT PM | M13: 2026-09-12 | N13: Open | O13: JCI operates all IT for Bosch for 18 months from 01 Jul 2028
A14: 6 | B14: 2.1 – As-Is Analysis | C14: 2026-10-01 | D14: SR = Scope | E14: Application inventory incomplete — not all ~500 apps captured in LeanIX / CMDB | F14: Unplanned apps discovered during migration; scope inflation; wave plan disruption | G14: Shadow IT; regional/local apps not registered centrally; incomplete CMDB entries | H14: 4 | I14: 3 | J14: =$H14*$I14 -> 12 | K14: Mandate all JCI business units to submit full app list; LeanIX discovery scan; app inventory freeze after QG2; regional validation workshops in AP/AM/EMEA | L14: JCI IT Architects + KPMG | M14: 2026-11-26 | N14: Open | O14: FRAME comparable: ~500 apps; use LeanIX as master landscape tool
A15: 7 | B15: 2.1 – As-Is Analysis | C15: 2026-10-01 | D15: RR = Resource | E15: JCI non-cooperative or slow in providing as-is IT data | F15: Incomplete landscape assessment; concept phase delayed; TSA service catalogue gaps | G15: JCI data confidentiality concerns pre-SPA; competing JCI operational priorities; unclear SPA obligations | H15: 3 | I15: 4 | J15: =$H15*$I15 -> 12 | K15: Establish data access protocol in SPA; weekly data request tracker; Steering Committee escalation path; KPMG facilitates JCI data sessions | L15: Bosch IT PM + KPMG | M15: 2026-09-30 | N15: Open | O15: Critical dependency: all Phase 2 analysis relies on JCI data provision
A16: 8 | B16: 2.2 – Architecture | C16: 2026-10-01 | D16: ScR = Schedule | E16: Co-locator data centre procurement delayed across 3 regions (AP / AM / EMEA) | F16: Regional hub not ready; all Phase 3 infrastructure build activities blocked for affected region | G16: Co-locator RFP takes longer than planned; AP/AM data centre capacity constraints; contract negotiation | H16: 2 | I16: 4 | J16: =$H16*$I16 -> 8 | K16: Co-locator selection decision by QG2; parallel RFP for all 3 regions; shortlist of 2 providers per region as contingency | L16: Bosch Procurement + Bosch Infra | M16: 2027-01-13 | N16: Open | O16: 3 regional co-locators required: AP hub, AM hub, EMEA hub
A17: 9 | B17: 2.3 – Migration Strategy | C17: 2026-10-01 | D17: QR = Quality | E17: Data separation rules not finalised before migration begins | F17: Data leakage risk; compliance breach; migration rework; legal disputes between Bosch and JCI | G17: Unclear data ownership; shared data between Bosch-retained and JCI carved-out entities | H17: 3 | I17: 4 | J17: =$H17*$I17 -> 12 | K17: Data ownership working group with Legal, JCI, and KPMG; non-selective migration approach (FRAME precedent); finalise rules and obtain sign-off before QG2 | L17: KPMG + Legal | M17: 2027-01-29 | N17: Open | O17: FRAME used non-selective migration approach — recommended for Trinity
A18: 10 | B18: 2.1 – Contracts | C18: 2026-10-01 | D18: LR = Legality | E18: Change-of-control clauses triggered on key vendor contracts (~6000 device licences) | F18: Vendor contract termination; service disruption Day 1; unplanned renegotiation costs | G18: ~6000 device licences and software contracts contain change-of-control clauses not yet reviewed | H18: 3 | I18: 3 | J18: =$H18*$I18 -> 9 | K18: Full contract audit completed by QG2; proactive vendor engagement initiated early; licence transfer agreements executed before SPA signing | L18: JCI Procurement + Legal | M18: 2028-04-01 | N18: Open | O18: ~6000 device licences in scope; change of control notifications to vendors in Phase 4
A19: 11 | B19: 2.3 – ERP Strategy | C19: 2026-10-01 | D19: SR = Scope | E19: ERP migration strategy (relocation vs split vs greenfield) not decided by QG2 | F19: Phase 3 SAP development cannot start; migration partner onboarding delayed; cost unknown | G19: Bosch and JCI management not aligned on ERP carve-out model; greenfield cost estimates pending | H19: 2 | I19: 4 | J19: =$H19*$I19 -> 8 | K19: ERP strategy workshop facilitated by KPMG by Dec 2026; decision escalated to Steering Committee; FRAME precedent (relocation/shell copy) used as default baseline | L19: ERP Architects + KPMG | M19: 2026-12-25 | N19: Open | O19: FRAME used shell copy approach; recommended for Trinity SAP landscape
A20: 12 | B20: 2.1 – Regional | C20: 2026-10-01 | D20: SR = Scope | E20: Brazil ERP tax complexity causes scope inflation and potential Day 1 exclusion | F20: Brazil CSO excluded from Day 1 go-live; manual tax compliance process; additional ERP development cost | G20: Brazil nota fiscal / SPED requirements unique; JCI Brazil SAP heavily customised for local tax law | H20: 4 | I20: 3 | J20: =$H20*$I20 -> 12 | K20: Engage Brazilian tax ERP specialist by Phase 2; assess scope of Brazilian localisations; develop Brazil-specific phased go-live contingency; timeline buffer for Brazil | L20: JCI ERP Team + KPMG | M20: 2027-01-22 | N20: Open | O20: Brazil flagged as extreme tax complexity in project guidelines
... A27: 19 | B27: 3.2 – ERP | C27: 2027-04-01 | D27: RR = Resource | E27: Migration partner (ERP / SAP) capacity not available per agreed schedule | F27: SAP shell copy delayed; SIT1/SIT2 milestones missed; UAT sign-off deadline at risk | G27: Migration partner engaged on competing programmes; exclusive SAP DMLT/SNP skill sets | H27: 3 | I27: 4 | J27: =$H27*$I27 -> 12 | K27: Contractual capacity commitments from migration partner signed by QG2; penalty clauses for schedule deviation; backup migration partner identified | L27: ERP Team + Procurement | M27: 2027-03-31 | N27: Open | O27: Single-source risk — specialist SAP migration skills market is tight
A28: 20 | B28: 3.5 – Security / IAM | C28: 2027-04-01 | D28: QR = Quality | E28: IAM / Identity Provider deployment delayed or defective | F28: User provisioning fails; application access blocked on Day 1; security compliance breach | G28: IAM integration complexity; Saviynt SC2 connector restricted to 10 days before closing; late identity data from JCI | H28: 3 | I28: 4 | K28: IAM deployment completed before QG3; connector configuration frozen 10 days pre-closing; fallback manual provisioning plan defined for Day 1 | L28: Bosch IAM Team | M28: 2027-05-28 | N28: Open | O28: FRAME benchmark: IAM/IdM implementation = 6-9 months; Saviynt SC2 10-day constraint is hard
A29: 21 | B29: 3.1 – Infrastructure | C29: 2027-04-01 | D29: CR = Customer Satisfaction | E29: Phone number migration incomplete on Day 1 at multiple sites | F29: External calls not possible from affected sites; customer-facing communication failure | G29: 4-8 week per-operator migration lead time; state-owned operators in AP/EMEA unresponsive | H29: 4 | I29: 3 | K29: Start all phone migration requests immediately after WAN cutover per site; temporary external numbers as fallback for operators with >8-week lead time; track per operator per site | L29: Bosch Telecom | M29: 2028-03-14 | N29: Open | O29: FRAME precedent: phone number migration was a realised risk — plan mitigations early
A30: 22 | B30: 3.3 – Applications | C30: 2027-04-01 | D30: SR = Scope | E30: Application wave planning disrupted by late-discovered apps (~500 apps) | F30: Wave 1 critical apps re-prioritised; migration packages need rework; schedule slip | G30: Shadow IT discovered during Phase 3; regional/local apps not in LeanIX; app owners unresponsive | H30: 3 | I30: 3 | K30: App inventory frozen after QG2; any new apps after QG2 require change control; wave plan buffer of 10% capacity for late discoveries | L30: KPMG + WS Leads | M30: 2027-05-19 | N30: Open | O30: FRAME had comparable scope inflation risk with ~500 apps
A31: 23 | B31: Phase 3 – Resources | C31: 2027-04-01 | D31: RR = Resource | E31: Bosch IT team overloaded across 8 parallel sub-workstreams in Phase 3 | F31: Task delays; quality degradation; key person burnout; critical path slippage | G31: 8 concurrent Phase 3 workstreams; same resources shared across infra, SAP, M365, CWP, IAM | H31: 4 | I31: 3 | K31: BigRoom planning to surface resource conflicts by QG2; resource plan validated monthly; external contractors for peak load (KPMG + specialist firms); IT PM tracks utilisation weekly | L31: IT PM + All WS Leads | M31: 2027-11-28 | N31: Open | O31: Phase 3 is the peak resource demand period for the entire programme
A32: 24 | B32: 3.3 – Applications | C32: 2027-04-01 | D32: QR = Quality | E32: Custom application adaptation not completed before end of Phase 3 | F32: Wave 1 migration delayed; critical business apps not ready for Merger Zone | G32: Dev team capacity; under-scoped custom app modifications; integration dependency complexity | H32: 3 | I32: 3 | K32: Custom app adaptation started immediately after QG3; dev team capacity confirmed; critical apps prioritised in Wave 1 | L32: Dev Teams + SWS3 | M32: 2027-07-25 | N32: Open | O32: ~500 apps — even small percentage of custom apps can create significant effort
A33: 25 | B33: 3.6 – IT Org | C33: 2027-04-01 | D33: QR = Quality | E33: Help desk not adequately staffed for multilingual 24×7 support across AP / AM / EMEA | F33: User incidents unresolved post-Day 1; SLA breach; business disruption; management escalations | G33: Multilingual staffing across 3 time zones; MSP/ITO contracting delays; training lag | H33: 2 | I33: 4 | K33: Help desk staffing plan approved by QG3; MSP contract signed by QG3; multilingual training programme (AP / AM / EMEA languages); IVR routing by region | L33: Bosch IT Ops + Bosch Procurement | M33: 2027-07-23 | N33: Open | O33: 24×5 multilingual support required at minimum; 24×7 for Day 1 hypercare
A34: 26 | B34: 3.5 – Security | C34: 2027-04-01 | D34: QR = Quality | E34: Cybersecurity breach during migration transition window | F34: Data exfiltration; production environment compromised; regulatory breach; project suspension | G34: Expanded attack surface during TSA; migration tooling access rights; weakened controls in transition | H34: 2 | I34: 5 | K34: Security architecture reviewed by CISO before QG3; penetration testing of Merger Zone pre-go-live; SOC monitoring active from Day 1; Zero Trust architecture for Merger Zone connectivity | L34: Bosch CISO | M34: 2027-07-19 | N34: Open | O34: Transition windows are prime targets; FRAME also had security risk in this phase
A35: 27 | B35: 3.5 – ITSM | C35: 2027-04-01 | D35: QR = Quality | E35: CMDB not fully populated before Day 1 (6000 assets / 180 sites) | F35: Incident management degraded post-Day 1; asset tracking gaps; ITSM SLA reporting unreliable | G35: Asset discovery at 180 sites takes longer than planned; JCI CMDB data quality poor | H35: 3 | I35: 2 | K35: CMDB build starts Phase 3; discovery tools deployed at top 30 sites by QG4; CMDB accuracy threshold defined (>80% by Day 1); manual data import for remaining sites | L35: Bosch ITSM Team | M35: 2027-07-09 | N35: Open | O35: ServiceNow CMDB target for 6000 assets; AP/AM sites = largest data volumes
A36: 28 | B36: 3.7 – TSA | C36: 2027-04-01 | D36: SR = Scope | E36: TSA service catalogue scope not agreed before QG2 | F36: TSA SLA gaps; disputed service ownership; Day 1 service gaps; legal disputes | G36: JCI and Bosch not aligned on service scope; unclear service exit criteria; pricing disputes | H36: 2 | I36: 4 | K36: TSA catalogue working group from Phase 2; service descriptions approved by both parties before QG2; legal review of all service descriptions; exit criteria defined per service | L36: JCI IT + Bosch IT + Legal | M36: 2027-05-13 | N36: Open | O36: 18-month TSA is the primary operational risk vehicle — catalogue must be watertight
A37: 29 | B37: 4.3 – ERP Migration | C37: 2027-12-01 | D37: QR = Quality | E37: SAP SIT1 or SIT2 reveals critical defects requiring extended remediation | F37: Remediation delay; UAT pushed out; Day 1 ERP go-live at risk; cascades to QG4 | G37: Incomplete interface mapping in Phase 3; SAP customisation conflicts; data quality issues | H37: 3 | I37: 4 | K37: Comprehensive SIT test plan agreed with business key users before SIT1; dedicated defect triage and remediation sprints; remediation schedule buffer of 15 days | L37: ERP Team + Business | M37: 2028-04-05 | N37: Open | O37: SIT1 target: Jan 2028; SIT2 target: Mar 2028 — both on critical path
A38: 30 | B38: 4.3 – ERP Migration | C38: 2027-12-01 | D38: BR = Business | E38: SAP interface breakage during shell copy — critical SAP-to-non-SAP interfaces | F38: Critical business processes fail Day 1; EDI down; supply chain disruption | G38: Incomplete interface catalogue; JCI interface customisations not captured in Phase 2 | H38: 3 | I38: 4 | K38: Full interface inventory completed by QG2; interface adaptation plan per interface; integration test plan covering all critical interfaces including EDI | L38: ERP Team + Integration Team | M38: 2027-06-11 | N38: Open | O38: FRAME interface mapping was a major Phase 3 effort — do not underestimate for Trinity
A39: 31 | B39: 4.2 – Client Device | C39: 2027-12-01 | D39: RR = Resource | E39: Client device migration wave behind schedule — 6000 devices / 180 sites | F39: Users unable to work on Day 1; help desk overwhelmed; productivity loss | G39: Remote site logistics; device age and hardware failure; network connectivity during reimaging | H39: 3 | I39: 3 | K39: Wave-based migration with AP/AM hubs first; pre-stage devices at regional hubs; regional IT team leads; 10% device buffer per wave for stragglers | L39: Bosch CWP + Regional IT | M39: 2028-03-22 | N39: Open | O39: 6000 devices across 180 sites — logistics risk is high, especially in AP
... A51: 43 | B51: 6.2 – MZ to Bosch Migration | C51: 2029-01-15 | D51: ScR = Schedule | E51: Bosch Active Directory integration (Merger Zone → Bosch) delayed in Phase 6 | F51: Client re-migration to Bosch domain blocked; TSA exit delayed; user access issues | G51: Bosch AD forest complexity; identity federation technical issues; naming convention conflicts | H51: 3 | I51: 3 | K51: Bosch AD integration design started in Phase 5; pilot with 100 test accounts in Oct 2028; rollback plan if federation fails; Bosch IAM lead dedicated resource from Phase 6 start | L51: Bosch IAM + Bosch AD Team | M51: 2029-02-25 | N51: Open | O51: AD integration = foundation for all Phase 6 client and app re-migrations
A52: 44 | B52: 6.2 – ERP Integration | C52: 2029-02-26 | D52: BR = Business | E52: ERP integration with Bosch parent systems fails in Phase 6 | F52: Bosch financial consolidation broken; audit trail gaps; manual reconciliation required | G52: Bosch ERP standard not compatible with Merger Zone SAP customisations; interface gaps | H52: 2 | I52: 4 | J52: =$H52*$I52 -> 8 | K52: Bosch SAP integration design from Phase 5; interface harmonisation plan agreed; reconciliation testing before production cutover; Bosch BW team prepares consolidated reporting | L52: ERP Team + Bosch IT | M52: 2029-04-22 | N52: Open | O52: ERP integration is on critical path for TSA exit of commercial IT services
A53: 45 | B53: 6.2 – App Migration | C53: 2029-01-15 | D53: SR = Scope | E53: Phase 6 app re-migration waves discover compatibility issues with Bosch environment | F53: Applications cannot migrate; extended TSA for affected apps; rework cost | G53: Bosch standard application portfolio differs; version incompatibilities; security policy conflicts | H53: 3 | I53: 3 | J53: =$H53*$I53 -> 9 | K53: Bosch application compatibility assessment in Phase 5; wave planning accounts for compatibility testing buffer; remediation sprint built into each wave timeline | L53: App Teams + Bosch IT | M53: 2029-07-01 | N53: Open | O53: ~500 apps need re-migration from Merger Zone to Bosch; compatibility unknown until Phase 5
A54: 46 | B54: 6.3 – TSA Exit | C54: 2029-07-02 | D54: ScR = Schedule | E54: TSA exit delayed beyond contractual 31 Dec 2029 deadline | F54: Post-TSA cost exposure; JCI relationship strain; operational dependency continuation | G54: Phase 6 migration waves delayed; Bosch AD integration issues; app re-migration complexity | H54: 3 | I54: 3 | J54: =$H54*$I54 -> 9 | K54: TSA exit milestones tracked monthly from Day 1; service exit criteria defined per service from Phase 3; exit readiness reviews from Q3 2029; contractual penalties for JCI if TSA extended beyond Dec 2029 due to JCI failure | L54: IT PM + JCI TSA Team | M54: 2029-11-14 | N54: Open | O54: TSA hard deadline = 31 Dec 2029 (18 months from 01 Jul 2028 Day 1)
A55: 47 | B55: Overall – PMO | C55: 2026-07-01 | D55: BtR = Budget | E55: Overall project budget overrun due to scope growth, resource shortage, or FX exposure | F55: Budget cap exceeded; delayed approvals; programme decisions delayed; quality compromised | G55: 180-site complexity; unexpected as-is findings; additional migration waves; EUR/USD FX exposure | H55: 3 | I55: 4 | J55: =$H55*$I55 -> 12 | K55: Monthly budget-to-complete tracking; change control process for all scope additions; 15% contingency reserve; Steering Committee budget review at every QG | L55: Finance + IT PM | M55: Permanent | N55: Open | O55: Trinity budget is multi-year (~3.5 years); FX and scope are primary drivers
A56: 48 | B56: Overall – PMO | C56: 2026-07-01 | D56: RR = Resource | E56: KPMG consulting capacity reduced or key consultant departs | F56: Methodology gaps; delayed concept deliverables; loss of institutional project knowledge | G56: KPMG reallocation to other engagements; consulting market demand; key staff turnover | H56: 2 | I56: 3 | J56: =$H56*$I56 -> 6 | K56: KPMG staffing plan contractually committed by project start; knowledge management in SharePoint updated weekly; backup consultants briefed from Phase 2 | L56: IT PM + KPMG | M56: Permanent | N56: Open | O56: KPMG is lead consulting partner across all workstreams in Phases 1-4
A57: 49 | B57: Overall – Legal | C57: 2026-07-01 | D57: LR = Legality | E57: GDPR / data privacy compliance gaps during cross-border data migration | F57: Regulatory fines; reputational damage; personal data breach notification obligation | G57: Data transferred across AP/EMEA/AM without adequate controls; migration tooling not GDPR-validated | H57: 2 | I57: 4 | J57: =$H57*$I57 -> 8 | K57: GDPR compliance review of all migration tools before Phase 3; DPIA for cross-border transfers; GDPR representative in Legal workstream; data minimisation approach adopted | L57: Legal + Bosch CISO | M57: 2028-06-30 | N57: Open | O57: GDPR applies across EMEA; Brazil LGPD applies in AM; China PIPL applies in AP
A58: 50 | B58: Overall – Governance | C58: 2026-07-01 | D58: RR = Resource | E58: Steering Committee engagement insufficient — decision velocity too slow | F58: Delayed decisions on critical issues; QG approvals delayed; workstream blockers unresolved | G58: SteerCo member availability (Bosch + JCI executives); competing strategic priorities | H58: 2 | I58: 4 | J58: =$H58*$I58 -> 8 | K58: Monthly SteerCo cadence from Phase 1; pre-aligned recommendations before each session; documented decision log; escalation tracker for blocking issues | L58: IT PM + Steering Committee | M58: Permanent | N58: Open | O58: FRAME lesson: early governance alignment is critical for speed of decision-making
A59: 51 | B59: Overall – Dependency | C59: 2026-07-01 | D59: BR = Business | E59: JCI cooperation deteriorates over the 3.5-year programme timeline | F59: Data provision delays; TSA service degradation; knowledge transfer gaps; exit disputes | G59: JCI management changes; competing JCI strategic priorities; relationship friction post-deal | H59: 2 | I59: 4 | J59: =$H59*$I59 -> 8 | K59: Joint governance forums (monthly); clear contractual obligations in SPA and TSA; escalation path to both CEOs; relationship management plan | L59: IT PM + Executive Leadership | M59: Permanent | N59: Open | O59: JCI cooperation is a dependency across all 6 phases — critical to maintain
A60: 52 | B60: Overall – PMO | C60: 2026-07-01 | D60: CR = Customer Satisfaction | E60: Stakeholder confidence erodes due to poor programme communications over 3.5 years | F60: Business disengagement; management resistance; press/media risk; programme credibility loss | G60: Complex multi-year programme; frequent design changes; multi-region stakeholder base | H60: 2 | I60: 3 | J60: =$H60*$I60 -> 6 | K60: Quarterly executive briefing pack; QG milestone communications; monthly stakeholder newsletter; Day 1 communication plan for all 8000 users | L60: IT PM + Comms | M60: Permanent | N60: Open | O60: Programme spans Jul 2026 – Dec 2029; stakeholder fatigue is a genuine risk
A61: 53 | B61: Overall – Regional | C61: 2026-07-01 | D61: ScR = Schedule | E61: AP region migration (largest) delayed — hub sites fall behind plan | F61: AP users not migrated on time; Merger Zone AP hub unstable; regional wave plan collapses | G61: Largest region by device count; complex country mix; WAN lead time variance across AP countries | H61: 3 | I61: 3 | J61: =$H61*$I61 -> 9 | K61: AP hub-first approach; dedicated AP IT Team; weekly AP migration status report; Steering Committee escalation if >10% behind wave plan | L61: AP IT Team + Bosch Infra | M61: 2028-02-23 | N61: Open | O61: AP is largest region by sites and device count; highest logistical complexity
A62: 54 | B62: Overall – India | C62: 2026-07-01 | D62: SR = Scope | E62: India RBIN (Restricted Bosch Internal Network) compliance conflicts with Merger Zone architecture | F62: India sites cannot connect to Merger Zone; workaround required; user access disrupted | G62: RBIN restricts external network connectivity; India-specific Bosch security policy | H62: 3 | I62: 3 | J62: =$H62*$I62 -> 9 | K62: India IT requirements scoped in Phase 2; RBIN exception process initiated with Bosch CISO; India-specific network design approved before QG2 | L62: Regional IT Leads + Bosch CISO | M62: 2026-11-20 | N62: Open | O62: India RBIN flagged as country-specific requirement in project guidelines

Sheet Explanation_History
B2: Information about method/template
B3: Scope of risk analysis: (Attention: Procedure partly changed compared to previous template version!) | E3: Project risks can generally be differed by product risks (e.g. product suitability, general conditions of product) and process risks (e.g. project management; development process or process of producing the project result). In the risk analysis both has to be covered.
B4: Update: Cycle and versions | E4: The risk analysis has to be updated regularly during the whole project duration - at least to each QA. The different states have to be versioned - the currently latest version has to be filed with the respective QA.
B5: Update: Procedure (Attention: Procedure partly changed compared to previous template version!) | E5: Updating the risk analysis, existing risks will be reassessed and new risk will be listed in the overview. By reassessing existing risks, the existing values can be overwritten with the new values because previous values are saved in the different versions of the document. Therefor old versions of the risk analysis have to be archived with the project documentation.
B6: Definition of actions (Attention: Procedure partly changed compared to previous template version!) | E6: At least for risks whose risk figure (RZ) is higher than or equal to the threshold value of 12, an action or a reason why no action is defined has to be named. It is recommended to define actions also to risks with high significance of effects (T). The threshold can be lowered (e.g. from 12 to 9) but not increased for the single project. To every action a responsible person and deadline have to be named.
B7: Tracking of risks and actions (Attention:Procedure partly changed compared to previous template version!) | E7: The document in which the actions are tracked has to be named in the cover sheet. Actions have to be done on schedule (requirement of C/AU)! If an action is processed and the status is set on 'completed', the risk has to be reassessed. Therefore the old values can simply be overwritten. If an action lowers the former significance of effects (T) of the risk, not only the value of T but also the effects (verbal description column F) have to be overwritten. If a risk is still high after completion of the action, a new action has to be defined. Traceability of the actions and their completion is given by the recording of the different versions of the risk analysis.
B8: Documentation | E8: To ensure the traceability of the risk analysis (requirement of C/AU), - the docment history (cover sheet) and - the column " entry date of risk" (for later listed risks) have to be filled in.
E9: If risks are escalated, this has to be definde as an action.
B10: Information about the makros | E10: To ensure the consistency of the template it is absolutely necessary that new lines are inserted exclusively about the button "New line".
B11: Additional Information about risk categories | E11: Explanation "Business Risk": Risk that the business processes of the customers do not work as needed
B13: Risk assessment:
C14: W - Probability of occurrence: | E14: 5 = very high 4 = high 3 = medium 2 = low 1 = unlikely
C15: T - Significance of effects: | E15: 5 = very severe 4 = severe 3 = medium 2 = low 1 = none
C16: RZ - Risk figure | E16: The risk figure supports the prioritization of risks and is the result of the product of W and T (RZ = W x T).
B19: Document History Template "AS-IS operation Risk Analysis"
B21: Version | C21: Release Date | D21: Author | E21: Description of Changes
B22: 1.0 | C22: 44725 | D22: BD/MIL-MIA Ladenburgerr | E22: Adaption to new BD-organisation
E23: Changes of Content:
E24: first version: Risk analysis template based on project risk analysis
